cloudflare_client/__init__.py
cloudflare_client-2.4.5.dist-info/METADATA
cloudflare_client-2.4.5.dist-info/WHEEL
cloudflare_client-2.4.5.dist-info/RECORD
