Metadata-Version: 2.1
Name: cloudflare_client
Version: 2.4.5
Summary: Advanced Python HTTP client based on tls-client, able to bypass Cloudflare UAM
Author: cloudflare-guy
Requires-Python: >=3.10,<4.0
Classifier: Programming Language :: Python :: 3
Classifier: Programming Language :: Python :: 3.10
Classifier: Programming Language :: Python :: 3.11
Classifier: Programming Language :: Python :: 3.12
Requires-Dist: browser-db (>=1.1.3,<2.0.0)
Requires-Dist: tls-client (>=1.0.1,<2.0.0)
Requires-Dist: typing-extensions (>=4.9.0,<5.0.0)
